ultraclassifier/__init__.py
ultraclassifier/python_api.py
ultraclassifier-0.2.6.dist-info/METADATA
ultraclassifier-0.2.6.dist-info/WHEEL
ultraclassifier-0.2.6.dist-info/entry_points.txt
ultraclassifier-0.2.6.dist-info/top_level.txt
ultraclassifier-0.2.6.dist-info/RECORD
