Metadata-Version: 2.4
Name: ultraclassifier
Version: 0.2.6
Author: weki
Classifier: Programming Language :: Python :: 3.10
Classifier: License :: OSI Approved :: MIT License
Requires-Python: >=3.8
Requires-Dist: torch
Requires-Dist: numpy
Requires-Dist: timm
Dynamic: author
Dynamic: classifier
Dynamic: requires-dist
Dynamic: requires-python
